{
  "project_info": {
    "project_number": "20433073751",
    "project_id": "myapp-9a677",
    "storage_bucket": "myapp-9a677.firebasestorage.app"
  },
  "client": [
    {
      "client_info": {
        "mobilesdk_app_id": "1:20433073751:android:6433b5a11c932125911512",
        "android_client_info": {
          "package_name": "com.example.myapplication"
        }
      },
      "oauth_client": [],
      "api_key": [
        {
          "current_key": "AIzaSyASK41eZB5Vz6paLQbbyvj_VMFl2AxL6w4"
        }
      ],
      "services": {
        "appinvite_service": {
          "other_platform_oauth_client": []
        }
      }
    }
  ],
  "configuration_version": "1"
}